{
  "updated_at": "2026-07-01T18:49:11+08:00",
  "raw": {
    "日期": "2026-07-01",
    "當月大台未沖銷契約量": 105030,
    "次月大台未沖銷契約量": 2094,
    "當月小台未沖銷契約量": 37970,
    "次月小台未沖銷契約量": 3578,
    "當月微台未沖銷契約量": 61252,
    "次月微台未沖銷契約量": 9275,
    "加權指數": 47018.99,
    "加權指數漲跌": 893.08,
    "加權指數當日高低差": 1058.4,
    "加權指數漲跌幅": 1.94,
    "加權指數成交量": 13678.18,
    "融資金額": null,
    "融券": null,
    "外資現貨買賣超": 32375599806,
    "外資大台期貨未平倉": -84168,
    "外資小台期貨未平倉": 3132,
    "外資微台期貨未平倉": 9993,
    "外資BC口數": 5395,
    "外資BC金額": 512049,
    "外資SC口數": 5902,
    "外資SC金額": 850822,
    "外資BP口數": 16575,
    "外資BP金額": 330118,
    "外資SP口數": 11800,
    "外資SP金額": 248103,
    "外資買方買權金額": 512049,
    "外資買方賣權金額": 330118,
    "外資(買)OP未平倉金額": -338773,
    "外資(賣)OP未平倉金額": 82015,
    "自營(自行)現貨買賣超": -172766157,
    "自營(避險)現貨買賣超": 6111242474,
    "自營大台期貨未平倉": 1592,
    "自營小台期貨未平倉": -6678,
    "自營微台期貨未平倉": -40245,
    "自營BC口數": 15639,
    "自營SC口數": 15078,
    "自營BC金額": 1304855,
    "自營SC金額": 1548933,
    "自營BP口數": 22109,
    "自營SP口數": 19915,
    "自營BP金額": 437916,
    "自營SP金額": 417665,
    "自營買方買權金額": 1304855,
    "自營買方賣權金額": 437916,
    "自營(買)OP未平倉金額": -244078,
    "自營(賣)OP未平倉金額": 20251,
    "全市場買權未沖銷": 110378,
    "全市場賣權未沖銷": 136931,
    "三大法人買權買方未平倉口數": 21040,
    "三大法人賣權買方未平倉口數": 38771,
    "今日市場(買)OP未平倉金額": 3171304,
    "今日市場(賣)OP未平倉金額": 1006289,
    "今日三大法人(買)OP未平倉金額": 1817513,
    "今日三大法人(賣)OP未平倉金額": 768581,
    "PCR成交量比": 113.71,
    "PCR未平倉比": 142.03,
    "小台未沖銷契約量": 45658,
    "三大法人多方小台口數": 8643,
    "三大法人空方小台口數": 12156,
    "微台未沖銷契約量": 80431,
    "三大法人多方微台口數": 13502,
    "三大法人空方微台口數": 43754
  },
  "stats": {
    "日期": "2026-07-01",
    "結算日": 3,
    "當次月大台留倉差增減": 591,
    "加權指數": 47018.99,
    "加權指數漲跌": 893.08,
    "加權指數當日高低差": 1058.4,
    "加權指數漲跌幅(%)": 1.94,
    "加權指數成交量(億)": 13678.18,
    "融資金額(億)": null,
    "融資金額變化量(億)": null,
    "融券(交易單位)": null,
    "融券單位變化量": null,
    "PCR與結算比": 8.879999999999995,
    "外資現貨買賣超": 323.75599806,
    "外資(大小台)期貨未平倉": -82885.35,
    "外資期貨未平倉與結算比": -15035.65000000001,
    "外資期貨未平倉與前日增減": -1031.5,
    "外資(買)OP未平倉口數": -507,
    "外資(買)OP未平倉金額": -338773,
    "外資(BC)OP未平倉金額與結算比": 103572,
    "外資(賣)OP未平倉口數": 4775,
    "外資(賣)OP未平倉金額": 82015,
    "外資(BP)OP未平倉金額與結算比": 6334,
    "外資買方買權/賣權比": 1.551,
    "外資買權/賣權比": -4.131,
    "自營(自行)現貨買賣超": -1.72766157,
    "自營(避險)現貨買賣超": 61.11242474,
    "自營(大小台)期貨未平倉": -2089.75,
    "自營(買)OP未平倉口數": 561,
    "自營(買)OP未平倉金額": -244078,
    "自營(BC)OP未平倉金額與結算比": 415146,
    "自營(賣)OP未平倉口數": 2194,
    "自營(賣)OP未平倉金額": 20251,
    "自營(BP)OP未平倉金額與結算比": 176979,
    "自營買方買權/賣權比": 2.98,
    "散戶買/賣權比": 5.699,
    "散戶看多": 37015,
    "散戶看空": 33502,
    "當次月小台留倉差增減": 989,
    "散戶未平倉": 3513,
    "微台散戶看多": 66929,
    "微台散戶看空": 36677,
    "當次月微台留倉差增減": -686.0,
    "微台散戶未平倉": 30252,
    "微台散戶多空比": 37.61236339222439
  },
  "options": {
    "日期": "2026-07-01",
    "結算日": 3,
    "當次月大台留倉差增減": 591,
    "加權指數": 47018.99,
    "加權指數漲跌": 893.08,
    "加權指數漲跌幅(%)": 1.94,
    "外資BC口數": 5395,
    "外資BC金額": 512049,
    "外資SC口數": 5902,
    "外資SC金額": 850822,
    "外資(SC增幅-BC增幅)金額": 59558,
    "外資BC/SC增幅比例": 4.749838914939112,
    "外資BP口數": 16575,
    "外資BP金額": 330118,
    "外資SP口數": 11800,
    "外資SP金額": 248103,
    "外資(SP增幅-BP增幅)金額": -12539,
    "外資BP/SP增幅比例": 0.6568552996074701,
    "自營BC口數": 15639,
    "自營BC金額": 1304855,
    "自營SC口數": 15078,
    "自營SC金額": 1548933,
    "自營(SC增幅-BC增幅)金額": 73061,
    "自營BC/SC增幅比例": 16.51430496883715,
    "自營BP口數": 22109,
    "自營BP金額": 437916,
    "自營SP口數": 19915,
    "自營SP金額": 417665,
    "自營(SP增幅-BP增幅)金額": 45664,
    "自營BP/SP增幅比例": 1.614816239157632
  }
}